MaaDebugger/__init__.py
MaaDebugger/__main__.py
MaaDebugger/__version__.py
MaaDebugger/assets/__init__.py
MaaDebugger/assets/favicon.png
MaaDebugger/maafw/__init__.py
MaaDebugger/maafw/launch_graph.py
MaaDebugger/utils/arg_parser.py
MaaDebugger/utils/img_tools.py
MaaDebugger/utils/input_checker.py
MaaDebugger/utils/js.py
MaaDebugger/utils/system.py
MaaDebugger/utils/update_checker/__init__.py
MaaDebugger/utils/update_checker/check.py
MaaDebugger/webpage/components/status_indicator.py
MaaDebugger/webpage/index_page/__init__.py
MaaDebugger/webpage/index_page/global_status.py
MaaDebugger/webpage/index_page/master_control.py
MaaDebugger/webpage/index_page/runtime_control.py
MaaDebugger/webpage/reco_page/__init__.py
MaaDebugger/webpage/traceback_page/__init__.py
maadebugger-1.17.0.dist-info/METADATA
maadebugger-1.17.0.dist-info/WHEEL
maadebugger-1.17.0.dist-info/entry_points.txt
maadebugger-1.17.0.dist-info/licenses/LICENSE
maadebugger-1.17.0.dist-info/RECORD
