Metadata-Version: 2.1
Name: MaaDebugger
Version: 1.17.0
Summary: MaaDebugger
Author: MaaXYZ
Project-URL: Homepage, https://github.com/MaaXYZ/MaaDebugger
Requires-Python: <=3.13,>=3.9
Requires-Dist: MaaFw>=5.4.1
Requires-Dist: nicegui<3.0,>=2.21
Requires-Dist: asyncify
Requires-Dist: pillow
Requires-Dist: packaging
